typers/__init__.py
typers/core.py
typers/exceptions.py
typers-0.2.0.dist-info/METADATA
typers-0.2.0.dist-info/WHEEL
typers-0.2.0.dist-info/licenses/LICENSE
typers-0.2.0.dist-info/RECORD
