Metadata-Version: 2.3
Name: typers
Version: 0.2.0
Summary: A package for type checking and error handling in Python.
Project-URL: Homepage, https://github.com/striatp/typers
Project-URL: Documentation, https://readthedocs.org
Project-URL: Repository, https://github.com/striatp/typers.git
Project-URL: Changelog, https://github.com/striatp/typers/main/blob/CHANGELOG.md
Author-email: Striatp <striatp@outlook.com>
Maintainer-email: Striatp <striatp@outlook.com>
License: MIT License
License-File: LICENSE
Keywords: error handling,type checking,validation
Classifier: Development Status :: 4 - Beta
Classifier: Programming Language :: Python
Requires-Python: >=3.8
